{
  "##characteristics#compile#binary_size#all": [
    7872
  ], 
  "##characteristics#compile#binary_size#all_unique": [
    7872
  ], 
  "##characteristics#compile#binary_size#center": 7872, 
  "##characteristics#compile#binary_size#center_imp": 1.0005081300813008, 
  "##characteristics#compile#binary_size#halfrange": 0, 
  "##characteristics#compile#binary_size#max": 7872, 
  "##characteristics#compile#binary_size#mean": 7872.0, 
  "##characteristics#compile#binary_size#mean_imp": 1.0005081300813008, 
  "##characteristics#compile#binary_size#min": 7872, 
  "##characteristics#compile#binary_size#min_imp": 1.0005081300813008, 
  "##characteristics#compile#binary_size#range": 0, 
  "##characteristics#compile#binary_size#range_percent": 0, 
  "##characteristics#compile#binary_size#repeats": 1, 
  "##characteristics#compile#compilation_success#all": [
    "yes"
  ], 
  "##characteristics#compile#compilation_success#all_unique": [
    "yes"
  ], 
  "##characteristics#compile#compilation_success#min": "yes", 
  "##characteristics#compile#compilation_success#min_imp": 0, 
  "##characteristics#compile#compilation_success#repeats": 1, 
  "##characteristics#compile#compilation_success_bool#all": [
    true
  ], 
  "##characteristics#compile#compilation_success_bool#all_unique": [
    true
  ], 
  "##characteristics#compile#compilation_success_bool#min": true, 
  "##characteristics#compile#compilation_success_bool#min_imp": 0, 
  "##characteristics#compile#compilation_success_bool#repeats": 1, 
  "##characteristics#compile#compilation_time#all": [
    0.4653890132904053
  ], 
  "##characteristics#compile#compilation_time#all_unique": [
    0.4653890132904053
  ], 
  "##characteristics#compile#compilation_time#center": 0.4653890132904053, 
  "##characteristics#compile#compilation_time#center_imp": 1.0136015528823765, 
  "##characteristics#compile#compilation_time#halfrange": 0.0, 
  "##characteristics#compile#compilation_time#max": 0.4653890132904053, 
  "##characteristics#compile#compilation_time#mean": 0.4653890132904053, 
  "##characteristics#compile#compilation_time#mean_imp": 1.0136015528823765, 
  "##characteristics#compile#compilation_time#min": 0.4653890132904053, 
  "##characteristics#compile#compilation_time#min_imp": 1.0136015528823765, 
  "##characteristics#compile#compilation_time#range": 0.0, 
  "##characteristics#compile#compilation_time#range_percent": 0.0, 
  "##characteristics#compile#compilation_time#repeats": 1, 
  "##characteristics#compile#compilation_time_with_module#all": [
    2.202713966369629
  ], 
  "##characteristics#compile#compilation_time_with_module#all_unique": [
    2.202713966369629
  ], 
  "##characteristics#compile#compilation_time_with_module#center": 2.202713966369629, 
  "##characteristics#compile#compilation_time_with_module#center_imp": 1.0471659249439216, 
  "##characteristics#compile#compilation_time_with_module#halfrange": 0.0, 
  "##characteristics#compile#compilation_time_with_module#max": 2.202713966369629, 
  "##characteristics#compile#compilation_time_with_module#mean": 2.202713966369629, 
  "##characteristics#compile#compilation_time_with_module#mean_imp": 1.0471659249439216, 
  "##characteristics#compile#compilation_time_with_module#min": 2.202713966369629, 
  "##characteristics#compile#compilation_time_with_module#min_imp": 1.0471659249439216, 
  "##characteristics#compile#compilation_time_with_module#range": 0.0, 
  "##characteristics#compile#compilation_time_with_module#range_percent": 0.0, 
  "##characteristics#compile#compilation_time_with_module#repeats": 1, 
  "##characteristics#compile#joined_compiler_flags#all": [
    "-O3 -fno-omit-frame-pointer -fno-tree-loop-optimize"
  ], 
  "##characteristics#compile#joined_compiler_flags#all_unique": [
    "-O3 -fno-omit-frame-pointer -fno-tree-loop-optimize"
  ], 
  "##characteristics#compile#joined_compiler_flags#min": "-O3 -fno-omit-frame-pointer -fno-tree-loop-optimize", 
  "##characteristics#compile#joined_compiler_flags#min_imp": 0, 
  "##characteristics#compile#joined_compiler_flags#repeats": 1, 
  "##characteristics#compile#md5_sum#all": [
    "751541cc221cd1d3238870a6a62072ff"
  ], 
  "##characteristics#compile#md5_sum#all_unique": [
    "751541cc221cd1d3238870a6a62072ff"
  ], 
  "##characteristics#compile#md5_sum#min": "751541cc221cd1d3238870a6a62072ff", 
  "##characteristics#compile#md5_sum#min_imp": 0, 
  "##characteristics#compile#md5_sum#repeats": 1, 
  "##characteristics#compile#obj_size#all": [
    3148
  ], 
  "##characteristics#compile#obj_size#all_unique": [
    3148
  ], 
  "##characteristics#compile#obj_size#center": 3148, 
  "##characteristics#compile#obj_size#center_imp": 1.0012706480304956, 
  "##characteristics#compile#obj_size#halfrange": 0, 
  "##characteristics#compile#obj_size#max": 3148, 
  "##characteristics#compile#obj_size#mean": 3148.0, 
  "##characteristics#compile#obj_size#mean_imp": 1.0012706480304956, 
  "##characteristics#compile#obj_size#min": 3148, 
  "##characteristics#compile#obj_size#min_imp": 1.0012706480304956, 
  "##characteristics#compile#obj_size#range": 0, 
  "##characteristics#compile#obj_size#range_percent": 0, 
  "##characteristics#compile#obj_size#repeats": 1, 
  "##characteristics#compile#obj_sizes#layer3.codelet__6.o#all": [
    988
  ], 
  "##characteristics#compile#obj_sizes#layer3.codelet__6.o#all_unique": [
    988
  ], 
  "##characteristics#compile#obj_sizes#layer3.codelet__6.o#center": 988, 
  "##characteristics#compile#obj_sizes#layer3.codelet__6.o#center_imp": 1.008097165991903, 
  "##characteristics#compile#obj_sizes#layer3.codelet__6.o#halfrange": 0, 
  "##characteristics#compile#obj_sizes#layer3.codelet__6.o#max": 988, 
  "##characteristics#compile#obj_sizes#layer3.codelet__6.o#mean": 988.0, 
  "##characteristics#compile#obj_sizes#layer3.codelet__6.o#mean_imp": 1.008097165991903, 
  "##characteristics#compile#obj_sizes#layer3.codelet__6.o#min": 988, 
  "##characteristics#compile#obj_sizes#layer3.codelet__6.o#min_imp": 1.008097165991903, 
  "##characteristics#compile#obj_sizes#layer3.codelet__6.o#range": 0, 
  "##characteristics#compile#obj_sizes#layer3.codelet__6.o#range_percent": 0, 
  "##characteristics#compile#obj_sizes#layer3.codelet__6.o#repeats": 1, 
  "##characteristics#compile#obj_sizes#layer3.codelet__6.wrapper.o#all": [
    2160
  ], 
  "##characteristics#compile#obj_sizes#layer3.codelet__6.wrapper.o#all_unique": [
    2160
  ], 
  "##characteristics#compile#obj_sizes#layer3.codelet__6.wrapper.o#center": 2160, 
  "##characteristics#compile#obj_sizes#layer3.codelet__6.wrapper.o#center_imp": 0.9981481481481481, 
  "##characteristics#compile#obj_sizes#layer3.codelet__6.wrapper.o#halfrange": 0, 
  "##characteristics#compile#obj_sizes#layer3.codelet__6.wrapper.o#max": 2160, 
  "##characteristics#compile#obj_sizes#layer3.codelet__6.wrapper.o#mean": 2160.0, 
  "##characteristics#compile#obj_sizes#layer3.codelet__6.wrapper.o#mean_imp": 0.9981481481481481, 
  "##characteristics#compile#obj_sizes#layer3.codelet__6.wrapper.o#min": 2160, 
  "##characteristics#compile#obj_sizes#layer3.codelet__6.wrapper.o#min_imp": 0.9981481481481481, 
  "##characteristics#compile#obj_sizes#layer3.codelet__6.wrapper.o#range": 0, 
  "##characteristics#compile#obj_sizes#layer3.codelet__6.wrapper.o#range_percent": 0, 
  "##characteristics#compile#obj_sizes#layer3.codelet__6.wrapper.o#repeats": 1, 
  "##characteristics#compile#program_git_hash#all": [
    "540987ceb20f9153dee31b7b45f428c8b3117198"
  ], 
  "##characteristics#compile#program_git_hash#all_unique": [
    "540987ceb20f9153dee31b7b45f428c8b3117198"
  ], 
  "##characteristics#compile#program_git_hash#min": "540987ceb20f9153dee31b7b45f428c8b3117198", 
  "##characteristics#compile#program_git_hash#min_imp": 0, 
  "##characteristics#compile#program_git_hash#repeats": 1, 
  "##characteristics#run#execution_time#all": [
    1.399937317989229e-05, 
    1.4000716607852871e-05, 
    1.4000403197799014e-05, 
    1.4006059825744012e-05
  ], 
  "##characteristics#run#execution_time#all_unique": [
    1.399937317989229e-05, 
    1.4000716607852871e-05, 
    1.4000403197799014e-05, 
    1.4006059825744012e-05
  ], 
  "##characteristics#run#execution_time#center": 1.400271650281815e-05, 
  "##characteristics#run#execution_time#center_imp": 1.1649783816236994, 
  "##characteristics#run#execution_time#halfrange": 3.3433229258610715e-09, 
  "##characteristics#run#execution_time#max": 1.4006059825744012e-05, 
  "##characteristics#run#execution_time#mean": 1.4001638202822047e-05, 
  "##characteristics#run#execution_time#mean_imp": 1.1668467958660362, 
  "##characteristics#run#execution_time#min": 1.399937317989229e-05, 
  "##characteristics#run#execution_time#min_imp": 1.161545309021628, 
  "##characteristics#run#execution_time#range": 6.686645851722143e-09, 
  "##characteristics#run#execution_time#range_percent": 0.00047763894610127036, 
  "##characteristics#run#execution_time#repeats": 4, 
  "##characteristics#run#execution_time_kernel_0#all": [
    8.263564, 
    8.264357, 
    8.264172, 
    8.267511
  ], 
  "##characteristics#run#execution_time_kernel_0#all_unique": [
    8.263564, 
    8.264357, 
    8.264172, 
    8.267511
  ], 
  "##characteristics#run#execution_time_kernel_0#center": 8.2655375, 
  "##characteristics#run#execution_time_kernel_0#center_imp": 1.1649783816236994, 
  "##characteristics#run#execution_time_kernel_0#halfrange": 0.0019735000000000724, 
  "##characteristics#run#execution_time_kernel_0#max": 8.267511, 
  "##characteristics#run#execution_time_kernel_0#mean": 8.264901, 
  "##characteristics#run#execution_time_kernel_0#mean_imp": 1.1668467958660362, 
  "##characteristics#run#execution_time_kernel_0#min": 8.263564, 
  "##characteristics#run#execution_time_kernel_0#min_imp": 1.161545309021628, 
  "##characteristics#run#execution_time_kernel_0#range": 0.003947000000000145, 
  "##characteristics#run#execution_time_kernel_0#range_percent": 0.0004776389461012397, 
  "##characteristics#run#execution_time_kernel_0#repeats": 4, 
  "##characteristics#run#execution_time_with_module#all": [
    8.798372983932495, 
    8.799391984939575, 
    8.799084901809692, 
    8.802594900131226
  ], 
  "##characteristics#run#execution_time_with_module#all_unique": [
    8.798372983932495, 
    8.799391984939575, 
    8.799084901809692, 
    8.802594900131226
  ], 
  "##characteristics#run#execution_time_with_module#center": 8.80048394203186, 
  "##characteristics#run#execution_time_with_module#center_imp": 1.154972440463314, 
  "##characteristics#run#execution_time_with_module#halfrange": 0.0021109580993652344, 
  "##characteristics#run#execution_time_with_module#max": 8.802594900131226, 
  "##characteristics#run#execution_time_with_module#mean": 8.799861192703247, 
  "##characteristics#run#execution_time_with_module#mean_imp": 1.1567205378331142, 
  "##characteristics#run#execution_time_with_module#min": 8.798372983932495, 
  "##characteristics#run#execution_time_with_module#min_imp": 1.151769646363386, 
  "##characteristics#run#execution_time_with_module#range": 0.004221916198730469, 
  "##characteristics#run#execution_time_with_module#range_percent": 0.00047985192335452153, 
  "##characteristics#run#execution_time_with_module#repeats": 4, 
  "##characteristics#run#repeat#all": [
    590281, 
    590281, 
    590281, 
    590281
  ], 
  "##characteristics#run#repeat#all_unique": [
    590281
  ], 
  "##characteristics#run#repeat#center": 590281, 
  "##characteristics#run#repeat#center_imp": 1.0, 
  "##characteristics#run#repeat#halfrange": 0, 
  "##characteristics#run#repeat#max": 590281, 
  "##characteristics#run#repeat#mean": 590281.0, 
  "##characteristics#run#repeat#mean_imp": 1.0, 
  "##characteristics#run#repeat#min": 590281, 
  "##characteristics#run#repeat#min_imp": 1.0, 
  "##characteristics#run#repeat#range": 0, 
  "##characteristics#run#repeat#range_percent": 0, 
  "##characteristics#run#repeat#repeats": 4, 
  "##characteristics#run#return_code#all": [
    0, 
    0, 
    0, 
    0
  ], 
  "##characteristics#run#return_code#all_unique": [
    0
  ], 
  "##characteristics#run#return_code#center": 0, 
  "##characteristics#run#return_code#halfrange": 0, 
  "##characteristics#run#return_code#max": 0, 
  "##characteristics#run#return_code#mean": 0.0, 
  "##characteristics#run#return_code#min": 0, 
  "##characteristics#run#return_code#min_imp": 1, 
  "##characteristics#run#return_code#range": 0, 
  "##characteristics#run#return_code#repeats": 4, 
  "##characteristics#run#run_success#all": [
    "yes", 
    "yes", 
    "yes", 
    "yes"
  ], 
  "##characteristics#run#run_success#all_unique": [
    "yes"
  ], 
  "##characteristics#run#run_success#min": "yes", 
  "##characteristics#run#run_success#min_imp": 1, 
  "##characteristics#run#run_success#repeats": 4, 
  "##characteristics#run#run_success_bool#all": [
    true, 
    true, 
    true, 
    true
  ], 
  "##characteristics#run#run_success_bool#all_unique": [
    true
  ], 
  "##characteristics#run#run_success_bool#min": true, 
  "##characteristics#run#run_success_bool#min_imp": 1, 
  "##characteristics#run#run_success_bool#repeats": 4, 
  "##characteristics#run#total_execution_time#all": [
    8.263564, 
    8.264357, 
    8.264172, 
    8.267511
  ], 
  "##characteristics#run#total_execution_time#all_unique": [
    8.263564, 
    8.264357, 
    8.264172, 
    8.267511
  ], 
  "##characteristics#run#total_execution_time#center": 8.2655375, 
  "##characteristics#run#total_execution_time#center_imp": 1.1649783816236994, 
  "##characteristics#run#total_execution_time#halfrange": 0.0019735000000000724, 
  "##characteristics#run#total_execution_time#max": 8.267511, 
  "##characteristics#run#total_execution_time#mean": 8.264901, 
  "##characteristics#run#total_execution_time#mean_imp": 1.1668467958660362, 
  "##characteristics#run#total_execution_time#min": 8.263564, 
  "##characteristics#run#total_execution_time#min_imp": 1.161545309021628, 
  "##characteristics#run#total_execution_time#range": 0.003947000000000145, 
  "##characteristics#run#total_execution_time#range_percent": 0.0004776389461012397, 
  "##characteristics#run#total_execution_time#repeats": 4
}
